<SequenceTableDataSet SchemaVersion="1.0" SequenceComment="" SequenceOperator="mcminns" SequenceSeqPathFileName="D:\MassHunter\Data\Mcminn\" SequencePreSeqAcqCommand="" SequencePostSeqAcqCommand="" SequencePreSeqDACommand="" SequencePostSeqDACommand="" SequenceReProcessing="False" SequenceInjectBarCodeMismatch="OnBarcodeMismatchInjectAnyway" SequenceOverwriteExistingData="True" SequenceDecoupleDataAnalysis="False" SequenceModifiedTimeStamp="" SequenceFileECMPath="" SequenceRecurringKeyword="" SequenceRecurringInterval="0" SequenceRecurringType="0" SequenceRecurringKeywordString="">
  <Sequence>
    <SequenceID>0</SequenceID>
    <SampleID>0</SampleID>
    <AcqMethodFileName>Rt-bDEX-SE_mcminn</AcqMethodFileName>
    <AcqMethodPathName>D:\MassHunter\Methods\</AcqMethodPathName>
    <Comment />
    <Completed>false</Completed>
    <DAMethodFileName />
    <DAMethodPathName />
    <DAReportPathFileName />
    <DataFileName>cedrol_mix_01</DataFileName>
    <DataPathName>D:\MassHunter\Data\Mcminn\</DataPathName>
    <Dilution>1</Dilution>
    <DualInjector>false</DualInjector>
    <DualInjectorExpectedBarcode />
    <DualInjectorVial>30</DualInjectorVial>
    <DualInjectorVolume>0</DualInjectorVolume>
    <EquilibrationTime>0</EquilibrationTime>
    <ExpectedBarcode />
    <InjectionsPerPosition>1</InjectionsPerPosition>
    <InjectorVolume>1</InjectorVolume>
    <InstrumentName>5977B GCMS</InstrumentName>
    <InstrumentType>SingleQuadrupole</InstrumentType>
    <Keyword />
    <KeywordString />
    <LevelName />
    <MatrixSpikeGroup />
    <Locked>false</Locked>
    <PlateCode />
    <PlatePosition>0</PlatePosition>
    <RackCode />
    <SampleGroup />
    <SampleInformation />
    <SampleName>cedrol_mix_01</SampleName>
    <SamplePosition>dummy</SamplePosition>
    <SamplePrepFileName />
    <SamplePrepPathName />
    <SampleType>Sample</SampleType>
    <TrayName />
    <UpdateResponseFactor>None</UpdateResponseFactor>
    <UpdateRetentionTime>None</UpdateRetentionTime>
    <UpdateQualifierRatios>None</UpdateQualifierRatios>
    <UpdateMassAssignments>None</UpdateMassAssignments>
    <UserDefined />
    <UserDefined1 />
    <UserDefined2 />
    <UserDefined3 />
    <UserDefined4 />
    <UserDefined5 />
    <UserDefined6 />
    <UserDefined7 />
    <UserDefined8 />
    <UserDefined9 />
    <Vial>30</Vial>
  </Sequence>
</SequenceTableDataSet>